s22rgb/__init__.py
s22rgb-0.0.3.dist-info/METADATA
s22rgb-0.0.3.dist-info/WHEEL
s22rgb-0.0.3.dist-info/top_level.txt
s22rgb-0.0.3.dist-info/RECORD
