Metadata-Version: 2.1
Name: s22rgb
Version: 0.0.3
Summary: Sentinel 2 to three bands rgb jpg
Home-page: https://github.com/ytkz11/s22rgb
Author: ytkz
Author-email: ytkz11@163.com
License: BSD License
Platform: all
Requires-Dist: zipfile
Requires-Dist: numpy
Requires-Dist: tqdm
